draftquality/__init__.py
draftquality/about.py
draftquality/feature_lists/__init__.py
draftquality/feature_lists/enwiki.py
draftquality/feature_lists/ptwiki.py
draftquality-0.0.4.dist-info/LICENSE
draftquality-0.0.4.dist-info/METADATA
draftquality-0.0.4.dist-info/WHEEL
draftquality-0.0.4.dist-info/top_level.txt
draftquality-0.0.4.dist-info/RECORD
